<?xml version="1.0" encoding="UTF-8"?>
<metadata xml:lang="id"><Esri><CreaDate>20171002</CreaDate><CreaTime>11000600</CreaTime><ArcGISFormat>1.0</ArcGISFormat><SyncOnce>TRUE</SyncOnce><DataProperties><lineage><Process ToolSource="c:\program files (x86)\arcgis\desktop10.5\ArcToolbox\Toolboxes\Conversion Tools.tbx\ASCIIToRaster" Date="20171002" Time="110006">ASCIIToRaster C:\Users\user\Documents\FOREST2020\SENTINEL\HASIL\topographic\topographic_correction_20170313\data\input\halimun-salak\asc\map-slope.asc C:\Users\user\Documents\FOREST2020\SENTINEL\HASIL\topographic\topographic_correction_20170313\data\input\halimun-salak\tif\slope.tif FLOAT</Process></lineage></DataProperties></Esri></metadata>
